aws_annoying/__init__.py
aws_annoying/mfa_config.py
aws_annoying/variable_loader.py
aws_annoying/cli/__init__.py
aws_annoying/cli/app.py
aws_annoying/cli/load_variables.py
aws_annoying/cli/logging_handler.py
aws_annoying/cli/main.py
aws_annoying/cli/ecs/__init__.py
aws_annoying/cli/ecs/_app.py
aws_annoying/cli/ecs/task_definition_lifecycle.py
aws_annoying/cli/ecs/wait_for_deployment.py
aws_annoying/cli/mfa/__init__.py
aws_annoying/cli/mfa/_app.py
aws_annoying/cli/mfa/configure.py
aws_annoying/cli/session_manager/__init__.py
aws_annoying/cli/session_manager/_app.py
aws_annoying/cli/session_manager/_common.py
aws_annoying/cli/session_manager/install.py
aws_annoying/cli/session_manager/port_forward.py
aws_annoying/cli/session_manager/start.py
aws_annoying/cli/session_manager/stop.py
aws_annoying/ecs/__init__.py
aws_annoying/ecs/check.py
aws_annoying/ecs/common.py
aws_annoying/ecs/errors.py
aws_annoying/ecs/wait_for.py
aws_annoying/session_manager/__init__.py
aws_annoying/session_manager/errors.py
aws_annoying/session_manager/session_manager.py
aws_annoying/session_manager/shortcuts.py
aws_annoying/utils/__init__.py
aws_annoying/utils/debugger.py
aws_annoying/utils/downloader.py
aws_annoying/utils/ec2.py
aws_annoying/utils/platform.py
aws_annoying/utils/timeout.py
aws_annoying-0.8.3.dist-info/METADATA
aws_annoying-0.8.3.dist-info/WHEEL
aws_annoying-0.8.3.dist-info/entry_points.txt
aws_annoying-0.8.3.dist-info/licenses/LICENSE
aws_annoying-0.8.3.dist-info/RECORD
