Metadata-Version: 2.4
Name: aws-annoying
Version: 0.8.3
Summary: Utils to handle some annoying AWS tasks.
Project-URL: Homepage, https://github.com/lasuillard-s/aws-annoying
Project-URL: Repository, https://github.com/lasuillard-s/aws-annoying.git
Project-URL: Issues, https://github.com/lasuillard-s/aws-annoying/issues
Author-email: Yuchan Lee <lasuillard@gmail.com>
License-Expression: MIT
License-File: LICENSE
Requires-Python: <4.0,>=3.9
Requires-Dist: boto3<2,>=1
Requires-Dist: pydantic<3,>=2
Requires-Dist: requests<3,>=2
Requires-Dist: tqdm<5,>=4
Requires-Dist: typer<1,>=0
